annotstein/__init__.py
annotstein/__main__.py
annotstein/cli/__init__.py
annotstein/cli/coco.py
annotstein/cli/main.py
annotstein/coco/__init__.py
annotstein/coco/ops.py
annotstein/coco/schemas.py
annotstein/common.py
annotstein/utils.py
annotstein/voc/__init__.py
annotstein/voc/ops.py
annotstein/yolo/__init__.py
annotstein/yolo/bbox.py
annotstein/yolo/common.py
annotstein/yolo/segmentation.py
annotstein-0.1.1.dist-info/LICENSE
annotstein-0.1.1.dist-info/METADATA
annotstein-0.1.1.dist-info/WHEEL
annotstein-0.1.1.dist-info/entry_points.txt
annotstein-0.1.1.dist-info/RECORD
