Metadata-Version: 2.1
Name: annotstein
Version: 0.1.1
Summary: 
License: MIT
Author: Carlos Miranda
Author-email: carlos.miralop@proton.me
Requires-Python: >=3.8
Classifier: License :: OSI Approved :: MIT License
Classifier: Programming Language :: Python :: 3
Classifier: Programming Language :: Python :: 3.8
Classifier: Programming Language :: Python :: 3.9
Classifier: Programming Language :: Python :: 3.10
Classifier: Programming Language :: Python :: 3.11
Classifier: Programming Language :: Python :: 3.12
Requires-Dist: pillow (>=10.0.0,<11.0.0)
Requires-Dist: pydantic (>=2.3.0,<3.0.0)
Requires-Dist: ruff (>=0.3.0,<0.4.0)
